apifairy/__init__.py
apifairy/core.py
apifairy/decorators.py
apifairy/exceptions.py
apifairy/fields.py
apifairy/templates/apifairy/elements.html
apifairy/templates/apifairy/rapidoc.html
apifairy/templates/apifairy/redoc.html
apifairy/templates/apifairy/swagger_ui.html
apifairy-1.5.1.dist-info/licenses/LICENSE
apifairy-1.5.1.dist-info/METADATA
apifairy-1.5.1.dist-info/WHEEL
apifairy-1.5.1.dist-info/top_level.txt
apifairy-1.5.1.dist-info/RECORD
