Metadata-Version: 2.4
Name: apifairy
Version: 1.5.1
Summary: A minimalistic API framework built on top of Flask, Marshmallow and friends.
Author-email: Miguel Grinberg <miguel.grinberg@gmail.com>
Project-URL: Homepage, https://github.com/miguelgrinberg/apifairy
Project-URL: Bug Tracker, https://github.com/miguelgrinberg/apifairy/issues
Classifier: Intended Audience :: Developers
Classifier: Programming Language :: Python :: 3
Classifier: License :: OSI Approved :: MIT License
Classifier: Operating System :: OS Independent
Requires-Python: >=3.9
License-File: LICENSE
Requires-Dist: flask>=1.1.0
Requires-Dist: flask-marshmallow
Requires-Dist: webargs>=8.3.0
Requires-Dist: flask-httpauth>=4
Requires-Dist: apispec>=4
Provides-Extra: docs
Requires-Dist: sphinx; extra == "docs"
Provides-Extra: dev
Requires-Dist: tox; extra == "dev"
Dynamic: license-file
